{
  "document": "Introduction to Internet of Things Assignment-Week 10 Solutions",
  "assignments": [
    {
      "title": "Week 10 Assignment",
      "questions": [
        {
          "questionNumber": 1,
          "questionText": "Smart city is an _______ system.",
          "options": [
            "a. local",
            "b. rural",
            "c. home",
            "d. urban"
          ],
          "correctAnswer": "d",
          "explanation": "Smart city is an urban system. (Please refer Lecture 46@8:02)"
        },
        {
          "questionNumber": 2,
          "questionText": "Which of the following is an area of focus in smart parking lots?",
          "options": [
            "a. Auto-routing of vehicles",
            "b. Auto-charging of vehicles",
            "c. Detection of slots in parking lots",
            "d. All of these"
          ],
          "correctAnswer": "d",
          "explanation": "Auto-routing, auto-charging and slot detection are focus areas in smart parking. (Please refer Lecture 46@19:42)"
        },
        {
          "questionNumber": 3,
          "questionText": "Select the statement(s) that are true for smart health.\nStatement I: Smart health is low-cost and portable.\nStatement II: Smart health allows remote check-ups and diagnosis.\nStatement III: Smart health enables effortless health monitoring.",
          "options": [
            "a. Statement I",
            "b. Statement II",
            "c. Statements I, II, and III",
            "d. None of these"
          ],
          "correctAnswer": "c",
          "explanation": "Smart health is low-cost/portable, supports remote check-ups & diagnosis, and enables effortless monitoring. (Please refer Lecture 46@26:12)"
        },
        {
          "questionNumber": 4,
          "questionText": "What refers to combining information from multiple sensor sources?",
          "options": [
            "a. Information collection",
            "b. Multi-sensor deployment",
            "c. Multi-sensor dissemination",
            "d. Multi-sensor data fusion"
          ],
          "correctAnswer": "d",
          "explanation": "Multi-sensor data fusion combines information from multiple sensor sources. (Please refer Lecture 47@6:52)"
        },
        {
          "questionNumber": 5,
          "questionText": "The ensemble of all the decisions happens at the _______ level (in data fusion).",
          "options": [
            "a. Feature level",
            "b. Decision level",
            "c. Pixel level",
            "d. All of these"
          ],
          "correctAnswer": "b",
          "explanation": "The ensemble of multiple decisions occurs at the decision level. (Please refer Lecture 47@11:10)"
        },
        {
          "questionNumber": 6,
          "questionText": "The smart parking system reduces traffic _______",
          "options": [
            "a. mobility",
            "b. area",
            "c. analysis",
            "d. congestion"
          ],
          "correctAnswer": "d",
          "explanation": "Smart parking reduces traffic congestion. (Please refer Lecture 47@16:58)"
        },
        {
          "questionNumber": 7,
          "questionText": "DLNA (used in HAN standards) expands to:",
          "options": [
            "a. Digital Lifestyle Network Alliance",
            "b. Digital Living Network Alliance",
            "c. Digital Lifestyle Network Algorithm",
            "d. None of these"
          ],
          "correctAnswer": "b",
          "explanation": "DLNA stands for Digital Living Network Alliance. (Please refer Lecture 48@13:49)"
        },
        {
          "questionNumber": 8,
          "questionText": "Smart home infrastructure cannot include wireless devices.",
          "options": [
            "a. True",
            "b. False"
          ],
          "correctAnswer": "b",
          "explanation": "Smart home infrastructure may include wired and/or wireless devices. (Please refer Lecture 48@6:17)"
        },
        {
          "questionNumber": 9,
          "questionText": "Which of the following is/are layers of Zigbee?",
          "options": [
            "a. Physical layer",
            "b. MAC layer",
            "c. Network layer",
            "d. All of these"
          ],
          "correctAnswer": "d",
          "explanation": "Zigbee layers include Physical, MAC and Network layers. (Please refer Lecture 48@16:23)"
        },
        {
          "questionNumber": 10,
          "questionText": "Which of the following is a property of V2X?",
          "options": [
            "a. Restricted to a single source",
            "b. Distributed architecture",
            "c. Both a and b",
            "d. Neither a nor b"
          ],
          "correctAnswer": "b",
          "explanation": "V2X follows a distributed architecture. (Please refer Lecture 49@12:06)"
        },
        {
          "questionNumber": 11,
          "questionText": "CCN is derived from ICN architecture.",
          "options": [
            "a. True",
            "b. False"
          ],
          "correctAnswer": "a",
          "explanation": "CCN is derived from Information Centric Networking (ICN). (Please refer Lecture 49@15:32)"
        },
        {
          "questionNumber": 12,
          "questionText": "Fill in the blank. In Vehicle-to-human/human-to-vehicle interaction, the human communicating with the vehicle _______",
          "options": [
            "a. is present in another vehicle",
            "b. is present in the same vehicle",
            "c. is present outside the vehicle on the roadside",
            "d. All of these"
          ],
          "correctAnswer": "c",
          "explanation": "In V2H/H2V, the human is present outside the vehicle on the roadside. (Please refer Lecture 49@3:13)"
        },
        {
          "questionNumber": 13,
          "questionText": "Fill in the blank. ICV communication is based on _______",
          "options": [
            "a. Dedicated Short Range Communication",
            "b. Directed Short Range Communication",
            "c. Dedicated Small Range Communication",
            "d. All of these"
          ],
          "correctAnswer": "a",
          "explanation": "ICV is based on Dedicated Short Range Communication (DSRC). (Please refer Lecture 50@7:22)"
        },
        {
          "questionNumber": 14,
          "questionText": "Which of the following is/are domains of VANET?",
          "options": [
            "a. In-vehicle",
            "b. Ad-hoc",
            "c. Both a and b",
            "d. Neither a nor b"
          ],
          "correctAnswer": "c",
          "explanation": "In-vehicle and Ad-hoc are domains of VANET. (Please refer Lecture 50@14:36)"
        },
        {
          "questionNumber": 15,
          "questionText": "The vehicles cannot be mobile in the Ad-hoc domain of VANET.",
          "options": [
            "a. True",
            "b. False"
          ],
          "correctAnswer": "b",
          "explanation": "Vehicles are mobile in the Ad-hoc domain of VANET. (Please refer Lecture 50@16:59)"
        }
      ]
    }
  ]
}